[
  {
    "title": "触れられたあとまで、肌に残る。フェザータッチが気持ちいい理由",
    "link": "https://note.com/miyaaromassage/n/ne16bfd01a389",
    "pubDate": "2026-07-20T01:17:16.000Z",
    "description": "強く押されたわけでもない。 続きをみる",
    "image": ""
  },
  {
    "title": "「感度は生まれつき」だと思ってない？",
    "link": "https://note.com/miyaaromassage/n/na62abb0b248b",
    "pubDate": "2026-07-17T04:34:01.000Z",
    "description": "「自分は感度が低いのかもしれない」 「触られているのはわかるけど、気持ちよさにつながらない」 続きをみる",
    "image": ""
  },
  {
    "title": "外イキ・中イキ・脳イキは何が違う？血流・骨盤底・脳で見る「快感のルート」",
    "link": "https://note.com/miyaaromassage/n/n9fe5fe9ee914",
    "pubDate": "2026-07-10T04:29:33.000Z",
    "description": "外イキ、中イキ、脳イキ。 言葉としてはよく聞くけど、実際に身体の中で何が違うのかは、かなり曖昧に語られがちです。 続きをみる",
    "image": ""
  },
  {
    "title": "指なら大丈夫なのに、挿入になるとネガティブになる理由",
    "link": "https://note.com/miyaaromassage/n/nf3e406ee0b12",
    "pubDate": "2026-06-29T04:46:25.000Z",
    "description": "続きをみる",
    "image": ""
  },
  {
    "title": "「好き」と「したい」と「気持ちいい」は、ぜんぶ別の話なのに恋愛感情だけで選ぶと、後で詰まる理由",
    "link": "https://note.com/miyaaromassage/n/ncf899aa3a74f",
    "pubDate": "2026-06-22T03:32:02.000Z",
    "description": "恋愛感情・性的な惹かれ・性欲・身体の快感は、必ずしも一致しない 続きをみる",
    "image": ""
  }
]
